{
  "patterns": [
    {
      "multvaludi": "",
      "multvalgtin": "",
      "modelidx": "",
      "itemidx": "",
      "productidx": "",
      "batchidx": "",
      "catalogidx": "",
      "refidx": "",
      "reorderidx": "",
      "partidx": "",
      "upcidx": "",
      "upnidx": "",
      "kitidx": "",
      "lotidx": "",
      "serialidx": "",
      "model": "Model\\s*(\\w+)",
      "udi": "UDI-?/?DI:?\\s*([\\w\\s(),]+)",
      "serial": "",
      "gtin": "",
      "product": "",
      "batch": "",
      "catalog": "",
      "part": "",
      "upc": "",
      "upn": "",
      "ref": "",
      "reorder": "",
      "item": "",
      "kit": "",
      "lot": "Lot\\s*#?(\\w+)"
    },
    {
      "multvaludi": "1,2,4",
      "multvalgtin": "",
      "modelidx": "",
      "itemidx": "",
      "productidx": "",
      "batchidx": "",
      "catalogidx": "",
      "refidx": "",
      "reorderidx": "",
      "partidx": "",
      "upcidx": "",
      "upnidx": "",
      "kitidx": "",
      "lotidx": "",
      "serialidx": "",
      "model": "",
      "udi": "UDI/DI\\s*(\\w+)\\s*\\(\\w+\\),\\s*(\\w+)\\s*\\(\\w+\\),(\\s*(\\w+)\\s*\\(\\w+\\))?",
      "serial": "",
      "gtin": "",
      "product": "",
      "batch": "",
      "catalog": "",
      "part": "",
      "upc": "",
      "upn": "",
      "ref": "REF\\s*:?\\s*([\\w-]+)",
      "reorder": "",
      "item": "",
      "kit": "",
      "lot": "Lot\\s*Numbers?:?\\s*([\\w\\s,]+)"
    },
    {
      "multvaludi": "",
      "multvalgtin": "",
      "modelidx": "",
      "itemidx": "",
      "productidx": "",
      "batchidx": "",
      "catalogidx": "",
      "refidx": "",
      "reorderidx": "",
      "partidx": "",
      "upcidx": "",
      "upnidx": "",
      "kitidx": "",
      "lotidx": "",
      "serialidx": "",
      "model": "",
      "udi": "UDI-?/?DI\\s*(\\d+)",
      "serial": "",
      "gtin": "",
      "product": "",
      "batch": "",
      "catalog": "Cat\\.\\s*(\\w+)",
      "part": "",
      "upc": "",
      "upn": "",
      "ref": "",
      "reorder": "",
      "item": "",
      "kit": "",
      "lot": "Lot\\s*#?(\\w+)"
    },
    {
      "multvaludi": "",
      "multvalgtin": "",
      "modelidx": "",
      "itemidx": "",
      "productidx": "",
      "batchidx": "",
      "catalogidx": "",
      "refidx": "",
      "reorderidx": "",
      "partidx": "",
      "upcidx": "",
      "upnidx": "",
      "kitidx": "",
      "lotidx": "0",
      "serialidx": "",
      "model": "",
      "udi": "",
      "serial": "",
      "gtin": "",
      "product": "",
      "batch": "",
      "catalog": "Cat\\.?\\s*(\\w+)",
      "part": "",
      "upc": "",
      "upn": "",
      "ref": "",
      "reorder": "",
      "item": "",
      "kit": "",
      "lot": "all lots"
    },
    {
      "multvaludi": "1,2,3",
      "multvalgtin": "",
      "modelidx": "",
      "itemidx": "",
      "productidx": "",
      "batchidx": "",
      "catalogidx": "",
      "refidx": "",
      "reorderidx": "",
      "partidx": "",
      "upcidx": "",
      "upnidx": "",
      "kitidx": "",
      "lotidx": "",
      "serialidx": "",
      "model": "",
      "udi": "UDI/?-?DI:?\\s*(\\w+)\\s*-\\s*each,\\s*(\\w+)\\s*-\\s*box,\\s*(\\w+)\\s*-\\s*case",
      "serial": "",
      "gtin": "",
      "product": "Product\\s*Code:\\s*(\\w+)",
      "batch": "",
      "catalog": "",
      "part": "",
      "upc": "",
      "upn": "",
      "ref": "",
      "reorder": "",
      "item": "",
      "kit": "",
      "lot": "Lot\\s*Numbers?:?\\s*([\\w,\\s]+)"
    }
  ]
}